<?xml version="1.0" encoding="utf-8"?>
<ModMetaData>
  <name>Land Fill (Terrains+) (Continued)</name>
  <packageId>Mlie.LandFill</packageId>
  <author>tikubonn</author>
  <url>https://github.com/emipa606/LandFill</url>
  <supportedVersions>
    <li>1.1</li>
    <li>1.2</li>
    <li>1.3</li>
    <li>1.4</li>
    <li>1.5</li>
    <li>1.6</li>
  </supportedVersions>
  <modDependencies />
  <loadAfter />
  <description>[img]https://i.imgur.com/buuPQel.png[/img]
Update of tremeloes mod
https://steamcommunity.com/sharedfiles/filedetails/?id=1274692210

- Might not work exactly as earlier as some features have been removed in the game since B18.

[img]https://i.imgur.com/pufA0kM.png[/img]

[table]
	[tr]
		[td][url=https://dsc.gg/mlie][img]https://i.imgur.com/zdzzBrc.png[/img][/url][/td]
		[td][url=https://github.com/emipa606/LandFill][img]https://i.imgur.com/kTkpTOE.png[/img][/url][/td]
    [/tr]
    [tr]
        [td][img]https://i.imgur.com/WjDSfUn.png[/img][/td]
        [td][img]https://i.imgur.com/Be8E2qJ.png[/img][/td]
    [/tr]
[/table]
	
[img]https://i.imgur.com/Z4GOv8H.png[/img]

Water, mud and marsh are friends. Take vantage of the terrain around you.
Add soils, roads, bridges, sliding floors and more things for you be able to terraforming.

[h1]Content[/h1]
[b]Soils:[/b] build overwater. Some are growable and placed indoor.
[b]Bridges:[/b] build overwater. Good to walk but deteriorate overtime.
[b]Roads:[/b] build overwater. Walk more efficiently.
[b]Foundations:[/b] build overwater. Set up for buildings.
[b]Slides:[/b] build over soils and floors. Increase the walk speed.
[b]Water:[/b] build over soils. Set up for terrains and slow down enemies.
[i]Obs.: overwater = over water, mud and marsh in most cases.[/i]

[h1]Balancing[/h1]
[b]Feel free to suggest value changes[/b]
Stuffs that rapidly deteriorate don't require much work or resources.
Bad stuffs starts with tribal colonies and don't require much work or resources.
The most part can't be removed but can be replaced (abuse of Primitive and Neutral soil).
Automated stuffs don't need energy and aren't breakable.
The pathCost of vanilla water, mud and marsh are slightly changed.

[h1]Compatibility[/h1]
Compatible with existent saves but may present inconsistencies with some floor mods.
[i](example: be able to set some terrains in strange places).[/i]

[h1]Links[/h1]
 • [url=https://www.dropbox.com/sh/xrafe1ym3o6tlxc/AAClk62jkX49WLru72QmYpu7a/Land%20Fill.rar?dl=0]Download[/url]
 • [url=https://ludeon.com/forums/index.php?topic=38984.0]Forum[/url]

[h1]Changelog[/h1]
[i]02/03/2018[/i]
   - Small fixes
[i]01/21/2018[/i]
   - Add a new terrain: neutral soil;
   - Small qol changes.


[img]https://i.imgur.com/PwoNOj4.png[/img]
[list]
[*] See if the the error persists if you just have this mod and its requirements active.
[*] If not, try adding your other mods until it happens again.
[*] Post your error-log using [url=https://steamcommunity.com/workshop/filedetails/?id=818773962]HugsLib[/url] or the standalone [url=https://steamcommunity.com/sharedfiles/filedetails/?id=2873415404]Uploader[/url] and command Ctrl+F12
[*] For best support, please use the Discord-channel for error-reporting.
[*] Do not report errors by making a discussion-thread, I get no notification of that.
[*] If you have the solution for a problem, please post it to the GitHub repository.
[*] Use [url=https://github.com/RimSort/RimSort/releases/latest]RimSort[/url] to sort your mods
[/list] 

[url=https://steamcommunity.com/sharedfiles/filedetails/changelog/2162781055][img]https://img.shields.io/github/v/release/emipa606/LandFill?label=latest%20version&amp;style=plastic&amp;color=9f1111&amp;labelColor=black[/img][/url] | tags:  terrain features</description>
  <modVersion IgnoreIfNoMatchingField="True">1.6.2</modVersion>
</ModMetaData>